[
  {
    "source": "404.html",
    "layout": "null",
    "title": "Диалектическая позитивная психология",
    "description": "Об искусстве жить, опираясь на материалистическую диалектику и позитивную психологию",
    "permalink": "/404.html",
    "recovered_from": "_site/404.html",
    "recovered_at": "2026-04-28",
    "recovered_static_html": true,
    "source_kind": "page"
  },
  {
    "source": "about-me.html",
    "layout": "null",
    "title": "Диалектическая позитивная психология",
    "description": "Об искусстве жить, опираясь на материалистическую диалектику и позитивную психологию",
    "permalink": "/about-me.html",
    "recovered_from": "_site/about-me.html",
    "recovered_at": "2026-04-28",
    "recovered_static_html": true,
    "source_kind": "page"
  },
  {
    "source": "about-site.html",
    "layout": "null",
    "title": "Диалектическая позитивная психология",
    "description": "Об искусстве жить, опираясь на материалистическую диалектику и позитивную психологию",
    "permalink": "/about-site.html",
    "recovered_from": "_site/about-site.html",
    "recovered_at": "2026-04-28",
    "recovered_static_html": true,
    "source_kind": "page"
  },
  {
    "source": "app/Docx-to-html.html",
    "layout": "null",
    "title": "Конвертер DOCX в HTML",
    "description": null,
    "permalink": "/app/Docx-to-html.html",
    "recovered_from": "_site/app/Docx-to-html.html",
    "recovered_at": "2026-04-28",
    "recovered_static_html": true,
    "body_class": "bg-[#17212B] text-white flex items-center justify-center min-h-screen p-4",
    "source_kind": "page"
  },
  {
    "source": "app/vk-m.html",
    "layout": "null",
    "title": "Конвертер чатов VK",
    "description": null,
    "permalink": "/app/vk-m.html",
    "recovered_from": "_site/app/vk-m.html",
    "recovered_at": "2026-04-28",
    "recovered_static_html": true,
    "body_class": "bg-[#17212B] text-white flex items-center justify-center min-h-screen p-4",
    "source_kind": "page"
  },
  {
    "source": "blog/dev-intellect/index.html",
    "layout": "null",
    "title": "Интеллектуальное развитие",
    "description": "Особенности и закономерности интеллектуального развития",
    "permalink": "/blog/dev-intellect/",
    "recovered_from": "_site/blog/dev-intellect/index.html",
    "recovered_at": "2026-04-28",
    "recovered_static_html": true,
    "image": "https://dial-pos-psych.ru/images/dev-intellect/cover.webp",
    "source_kind": "page"
  },
  {
    "source": "blog/effect-person/index.html",
    "layout": "null",
    "title": "Эффективная личность",
    "description": "Качественные и количественные параметры психических процессов, состояний и свойств эффективной личности",
    "permalink": "/blog/effect-person/",
    "recovered_from": "_site/blog/effect-person/index.html",
    "recovered_at": "2026-04-28",
    "recovered_static_html": true,
    "image": "https://dial-pos-psych.ru/images/effect-person/cover.webp",
    "source_kind": "page"
  },
  {
    "source": "blog/free-courses-mine/index.html",
    "layout": "null",
    "title": "Мои курсы",
    "description": "Курсы по позитивной психологии от Артёма Пирога",
    "permalink": "/blog/free-courses-mine/",
    "recovered_from": "_site/blog/free-courses-mine/index.html",
    "recovered_at": "2026-04-28",
    "recovered_static_html": true,
    "image": "https://dial-pos-psych.ru/images/free-courses-mine/cover.webp",
    "source_kind": "page"
  },
  {
    "source": "blog/free-courses-pp/index.html",
    "layout": "null",
    "title": "Курсы по позитивной психологии",
    "description": "Лекции по позитивной психологии от преподавтелей из лучших университетов мира",
    "permalink": "/blog/free-courses-pp/",
    "recovered_from": "_site/blog/free-courses-pp/index.html",
    "recovered_at": "2026-04-28",
    "recovered_static_html": true,
    "image": "https://dial-pos-psych.ru/images/free-courses-pp/cover.webp",
    "source_kind": "page"
  },
  {
    "source": "blog/hap-pactice/index.html",
    "layout": "null",
    "title": "Практики счастья",
    "description": "Проверенные исследованиями действия, которые, как было показано, повышают счастье и благополучие",
    "permalink": "/blog/hap-pactice/",
    "recovered_from": "_site/blog/hap-pactice/index.html",
    "recovered_at": "2026-04-28",
    "recovered_static_html": true,
    "image": "https://dial-pos-psych.ru/images/hap-pactice/cover.webp",
    "source_kind": "page"
  },
  {
    "source": "blog/hap-pactice/page2/index.html",
    "layout": "null",
    "title": "Практики счастья Страница 2",
    "description": "Проверенные исследованиями действия, которые, как было показано, повышают счастье и благополучие",
    "permalink": "/blog/hap-pactice/page2/",
    "recovered_from": "_site/blog/hap-pactice/page2/index.html",
    "recovered_at": "2026-04-28",
    "recovered_static_html": true,
    "image": "https://dial-pos-psych.ru/images/hap-pactice/cover.webp",
    "source_kind": "page"
  },
  {
    "source": "blog/index.html",
    "layout": "null",
    "title": "Все материалы сайта",
    "description": "Все статьи сайта Диалектическая позитивная психология",
    "permalink": "/blog/",
    "recovered_from": "_site/blog/index.html",
    "recovered_at": "2026-04-28",
    "recovered_static_html": true,
    "source_kind": "page"
  },
  {
    "source": "blog/ker-course-free/index.html",
    "layout": "null",
    "title": "Курс Эффективного Родителя",
    "description": "Обучение родителей самым эффективным техникам общения с детьми",
    "permalink": "/blog/ker-course-free/",
    "recovered_from": "_site/blog/ker-course-free/index.html",
    "recovered_at": "2026-04-28",
    "recovered_static_html": true,
    "image": "https://dial-pos-psych.ru/images/ker-course-free/cover.webp",
    "source_kind": "page"
  },
  {
    "source": "blog/man-hap-harvard/index.html",
    "layout": "null",
    "title": "Текстовые материалы курса “Управление счастьем” (Гарвард)",
    "description": "Текстовые материалы курса “Управление счастьем” (Гарвард)",
    "permalink": "/blog/man-hap-harvard/",
    "recovered_from": "_site/blog/man-hap-harvard/index.html",
    "recovered_at": "2026-04-28",
    "recovered_static_html": true,
    "image": "https://dial-pos-psych.ru/images/man-hap-harvard/cover.webp",
    "source_kind": "page"
  },
  {
    "source": "blog/man-hap-harvard/page2/index.html",
    "layout": "null",
    "title": "Текстовые материалы курса “Управление счастьем” (Гарвард) Страница 2",
    "description": "Текстовые материалы курса “Управление счастьем” (Гарвард)",
    "permalink": "/blog/man-hap-harvard/page2/",
    "recovered_from": "_site/blog/man-hap-harvard/page2/index.html",
    "recovered_at": "2026-04-28",
    "recovered_static_html": true,
    "image": "https://dial-pos-psych.ru/images/man-hap-harvard/cover.webp",
    "source_kind": "page"
  },
  {
    "source": "blog/man-hap-harvard/page3/index.html",
    "layout": "null",
    "title": "Текстовые материалы курса “Управление счастьем” (Гарвард) Страница 3",
    "description": "Текстовые материалы курса “Управление счастьем” (Гарвард)",
    "permalink": "/blog/man-hap-harvard/page3/",
    "recovered_from": "_site/blog/man-hap-harvard/page3/index.html",
    "recovered_at": "2026-04-28",
    "recovered_static_html": true,
    "image": "https://dial-pos-psych.ru/images/man-hap-harvard/cover.webp",
    "source_kind": "page"
  },
  {
    "source": "blog/man-hap-harvard/page4/index.html",
    "layout": "null",
    "title": "Текстовые материалы курса “Управление счастьем” (Гарвард) Страница 4",
    "description": "Текстовые материалы курса “Управление счастьем” (Гарвард)",
    "permalink": "/blog/man-hap-harvard/page4/",
    "recovered_from": "_site/blog/man-hap-harvard/page4/index.html",
    "recovered_at": "2026-04-28",
    "recovered_static_html": true,
    "image": "https://dial-pos-psych.ru/images/man-hap-harvard/cover.webp",
    "source_kind": "page"
  },
  {
    "source": "blog/man-hap-harvard-vid/index.html",
    "layout": "null",
    "title": "Видеолекции курса Управление счастьем (Гарвард)",
    "description": "Все видеолекции из 6-ти модулей курса",
    "permalink": "/blog/man-hap-harvard-vid/",
    "recovered_from": "_site/blog/man-hap-harvard-vid/index.html",
    "recovered_at": "2026-04-28",
    "recovered_static_html": true,
    "image": "https://dial-pos-psych.ru/images/man-hap-harvard-vid/cover.webp",
    "source_kind": "page"
  },
  {
    "source": "blog/page10/index.html",
    "layout": "null",
    "title": "Все материалы сайта Страница 10",
    "description": "Все статьи сайта Диалектическая позитивная психология",
    "permalink": "/blog/page10/",
    "recovered_from": "_site/blog/page10/index.html",
    "recovered_at": "2026-04-28",
    "recovered_static_html": true,
    "source_kind": "page"
  },
  {
    "source": "blog/page11/index.html",
    "layout": "null",
    "title": "Все материалы сайта Страница 11",
    "description": "Все статьи сайта Диалектическая позитивная психология",
    "permalink": "/blog/page11/",
    "recovered_from": "_site/blog/page11/index.html",
    "recovered_at": "2026-04-28",
    "recovered_static_html": true,
    "source_kind": "page"
  },
  {
    "source": "blog/page12/index.html",
    "layout": "null",
    "title": "Все материалы сайта Страница 12",
    "description": "Все статьи сайта Диалектическая позитивная психология",
    "permalink": "/blog/page12/",
    "recovered_from": "_site/blog/page12/index.html",
    "recovered_at": "2026-04-28",
    "recovered_static_html": true,
    "source_kind": "page"
  },
  {
    "source": "blog/page13/index.html",
    "layout": "null",
    "title": "Все материалы сайта Страница 13",
    "description": "Все статьи сайта Диалектическая позитивная психология",
    "permalink": "/blog/page13/",
    "recovered_from": "_site/blog/page13/index.html",
    "recovered_at": "2026-04-28",
    "recovered_static_html": true,
    "source_kind": "page"
  },
  {
    "source": "blog/page14/index.html",
    "layout": "null",
    "title": "Все материалы сайта Страница 14",
    "description": "Все статьи сайта Диалектическая позитивная психология",
    "permalink": "/blog/page14/",
    "recovered_from": "_site/blog/page14/index.html",
    "recovered_at": "2026-04-28",
    "recovered_static_html": true,
    "source_kind": "page"
  },
  {
    "source": "blog/page15/index.html",
    "layout": "null",
    "title": "Все материалы сайта Страница 15",
    "description": "Все статьи сайта Диалектическая позитивная психология",
    "permalink": "/blog/page15/",
    "recovered_from": "_site/blog/page15/index.html",
    "recovered_at": "2026-04-28",
    "recovered_static_html": true,
    "source_kind": "page"
  },
  {
    "source": "blog/page16/index.html",
    "layout": "null",
    "title": "Все материалы сайта Страница 16",
    "description": "Все статьи сайта Диалектическая позитивная психология",
    "permalink": "/blog/page16/",
    "recovered_from": "_site/blog/page16/index.html",
    "recovered_at": "2026-04-28",
    "recovered_static_html": true,
    "source_kind": "page"
  },
  {
    "source": "blog/page17/index.html",
    "layout": "null",
    "title": "Все материалы сайта Страница 17",
    "description": "Все статьи сайта Диалектическая позитивная психология",
    "permalink": "/blog/page17/",
    "recovered_from": "_site/blog/page17/index.html",
    "recovered_at": "2026-04-28",
    "recovered_static_html": true,
    "source_kind": "page"
  },
  {
    "source": "blog/page18/index.html",
    "layout": "null",
    "title": "Все материалы сайта Страница 18",
    "description": "Все статьи сайта Диалектическая позитивная психология",
    "permalink": "/blog/page18/",
    "recovered_from": "_site/blog/page18/index.html",
    "recovered_at": "2026-04-28",
    "recovered_static_html": true,
    "source_kind": "page"
  },
  {
    "source": "blog/page19/index.html",
    "layout": "null",
    "title": "Все материалы сайта Страница 19",
    "description": "Все статьи сайта Диалектическая позитивная психология",
    "permalink": "/blog/page19/",
    "recovered_from": "_site/blog/page19/index.html",
    "recovered_at": "2026-04-28",
    "recovered_static_html": true,
    "source_kind": "page"
  },
  {
    "source": "blog/page2/index.html",
    "layout": "null",
    "title": "Все материалы сайта Страница 2",
    "description": "Все статьи сайта Диалектическая позитивная психология",
    "permalink": "/blog/page2/",
    "recovered_from": "_site/blog/page2/index.html",
    "recovered_at": "2026-04-28",
    "recovered_static_html": true,
    "source_kind": "page"
  },
  {
    "source": "blog/page20/index.html",
    "layout": "null",
    "title": "Все материалы сайта Страница 20",
    "description": "Все статьи сайта Диалектическая позитивная психология",
    "permalink": "/blog/page20/",
    "recovered_from": "_site/blog/page20/index.html",
    "recovered_at": "2026-04-28",
    "recovered_static_html": true,
    "source_kind": "page"
  },
  {
    "source": "blog/page21/index.html",
    "layout": "null",
    "title": "Все материалы сайта Страница 21",
    "description": "Все статьи сайта Диалектическая позитивная психология",
    "permalink": "/blog/page21/",
    "recovered_from": "_site/blog/page21/index.html",
    "recovered_at": "2026-04-28",
    "recovered_static_html": true,
    "source_kind": "page"
  },
  {
    "source": "blog/page3/index.html",
    "layout": "null",
    "title": "Все материалы сайта Страница 3",
    "description": "Все статьи сайта Диалектическая позитивная психология",
    "permalink": "/blog/page3/",
    "recovered_from": "_site/blog/page3/index.html",
    "recovered_at": "2026-04-28",
    "recovered_static_html": true,
    "source_kind": "page"
  },
  {
    "source": "blog/page4/index.html",
    "layout": "null",
    "title": "Все материалы сайта Страница 4",
    "description": "Все статьи сайта Диалектическая позитивная психология",
    "permalink": "/blog/page4/",
    "recovered_from": "_site/blog/page4/index.html",
    "recovered_at": "2026-04-28",
    "recovered_static_html": true,
    "source_kind": "page"
  },
  {
    "source": "blog/page5/index.html",
    "layout": "null",
    "title": "Все материалы сайта Страница 5",
    "description": "Все статьи сайта Диалектическая позитивная психология",
    "permalink": "/blog/page5/",
    "recovered_from": "_site/blog/page5/index.html",
    "recovered_at": "2026-04-28",
    "recovered_static_html": true,
    "source_kind": "page"
  },
  {
    "source": "blog/page6/index.html",
    "layout": "null",
    "title": "Все материалы сайта Страница 6",
    "description": "Все статьи сайта Диалектическая позитивная психология",
    "permalink": "/blog/page6/",
    "recovered_from": "_site/blog/page6/index.html",
    "recovered_at": "2026-04-28",
    "recovered_static_html": true,
    "source_kind": "page"
  },
  {
    "source": "blog/page7/index.html",
    "layout": "null",
    "title": "Все материалы сайта Страница 7",
    "description": "Все статьи сайта Диалектическая позитивная психология",
    "permalink": "/blog/page7/",
    "recovered_from": "_site/blog/page7/index.html",
    "recovered_at": "2026-04-28",
    "recovered_static_html": true,
    "source_kind": "page"
  },
  {
    "source": "blog/page8/index.html",
    "layout": "null",
    "title": "Все материалы сайта Страница 8",
    "description": "Все статьи сайта Диалектическая позитивная психология",
    "permalink": "/blog/page8/",
    "recovered_from": "_site/blog/page8/index.html",
    "recovered_at": "2026-04-28",
    "recovered_static_html": true,
    "source_kind": "page"
  },
  {
    "source": "blog/page9/index.html",
    "layout": "null",
    "title": "Все материалы сайта Страница 9",
    "description": "Все статьи сайта Диалектическая позитивная психология",
    "permalink": "/blog/page9/",
    "recovered_from": "_site/blog/page9/index.html",
    "recovered_at": "2026-04-28",
    "recovered_static_html": true,
    "source_kind": "page"
  },
  {
    "source": "blog/pos-relat/index.html",
    "layout": "null",
    "title": "Позитивные отношения",
    "description": "Хорошие взаимоотношения с другими людьми самым серьезным образом влияют на благополучие человека",
    "permalink": "/blog/pos-relat/",
    "recovered_from": "_site/blog/pos-relat/index.html",
    "recovered_at": "2026-04-28",
    "recovered_static_html": true,
    "image": "https://dial-pos-psych.ru/images/pos-relat/cover.webp",
    "source_kind": "page"
  },
  {
    "source": "blog/sci-hap-berkeley/index.html",
    "layout": "null",
    "title": "Текстовые материалы курса “Наука о счастье” (Беркли)",
    "description": "Текстовые материалы курса “Наука о счастье” (Беркли)",
    "permalink": "/blog/sci-hap-berkeley/",
    "recovered_from": "_site/blog/sci-hap-berkeley/index.html",
    "recovered_at": "2026-04-28",
    "recovered_static_html": true,
    "image": "https://dial-pos-psych.ru/images/sci-hap-berkeley/cover.webp",
    "source_kind": "page"
  },
  {
    "source": "blog/sci-hap-berkeley/page2/index.html",
    "layout": "null",
    "title": "Текстовые материалы курса “Наука о счастье” (Беркли) Страница 2",
    "description": "Текстовые материалы курса “Наука о счастье” (Беркли)",
    "permalink": "/blog/sci-hap-berkeley/page2/",
    "recovered_from": "_site/blog/sci-hap-berkeley/page2/index.html",
    "recovered_at": "2026-04-28",
    "recovered_static_html": true,
    "image": "https://dial-pos-psych.ru/images/sci-hap-berkeley/cover.webp",
    "source_kind": "page"
  },
  {
    "source": "blog/sci-hap-berkeley/page3/index.html",
    "layout": "null",
    "title": "Текстовые материалы курса “Наука о счастье” (Беркли) Страница 3",
    "description": "Текстовые материалы курса “Наука о счастье” (Беркли)",
    "permalink": "/blog/sci-hap-berkeley/page3/",
    "recovered_from": "_site/blog/sci-hap-berkeley/page3/index.html",
    "recovered_at": "2026-04-28",
    "recovered_static_html": true,
    "image": "https://dial-pos-psych.ru/images/sci-hap-berkeley/cover.webp",
    "source_kind": "page"
  },
  {
    "source": "blog/sci-hap-berkeley/page4/index.html",
    "layout": "null",
    "title": "Текстовые материалы курса “Наука о счастье” (Беркли) Страница 4",
    "description": "Текстовые материалы курса “Наука о счастье” (Беркли)",
    "permalink": "/blog/sci-hap-berkeley/page4/",
    "recovered_from": "_site/blog/sci-hap-berkeley/page4/index.html",
    "recovered_at": "2026-04-28",
    "recovered_static_html": true,
    "image": "https://dial-pos-psych.ru/images/sci-hap-berkeley/cover.webp",
    "source_kind": "page"
  },
  {
    "source": "blog/sci-hap-berkeley/page5/index.html",
    "layout": "null",
    "title": "Текстовые материалы курса “Наука о счастье” (Беркли) Страница 5",
    "description": "Текстовые материалы курса “Наука о счастье” (Беркли)",
    "permalink": "/blog/sci-hap-berkeley/page5/",
    "recovered_from": "_site/blog/sci-hap-berkeley/page5/index.html",
    "recovered_at": "2026-04-28",
    "recovered_static_html": true,
    "image": "https://dial-pos-psych.ru/images/sci-hap-berkeley/cover.webp",
    "source_kind": "page"
  },
  {
    "source": "blog/sci-hap-berkeley/page6/index.html",
    "layout": "null",
    "title": "Текстовые материалы курса “Наука о счастье” (Беркли) Страница 6",
    "description": "Текстовые материалы курса “Наука о счастье” (Беркли)",
    "permalink": "/blog/sci-hap-berkeley/page6/",
    "recovered_from": "_site/blog/sci-hap-berkeley/page6/index.html",
    "recovered_at": "2026-04-28",
    "recovered_static_html": true,
    "image": "https://dial-pos-psych.ru/images/sci-hap-berkeley/cover.webp",
    "source_kind": "page"
  },
  {
    "source": "blog/sci-hap-berkeley/page7/index.html",
    "layout": "null",
    "title": "Текстовые материалы курса “Наука о счастье” (Беркли) Страница 7",
    "description": "Текстовые материалы курса “Наука о счастье” (Беркли)",
    "permalink": "/blog/sci-hap-berkeley/page7/",
    "recovered_from": "_site/blog/sci-hap-berkeley/page7/index.html",
    "recovered_at": "2026-04-28",
    "recovered_static_html": true,
    "image": "https://dial-pos-psych.ru/images/sci-hap-berkeley/cover.webp",
    "source_kind": "page"
  },
  {
    "source": "blog/sci-hap-berkeley/page8/index.html",
    "layout": "null",
    "title": "Текстовые материалы курса “Наука о счастье” (Беркли) Страница 8",
    "description": "Текстовые материалы курса “Наука о счастье” (Беркли)",
    "permalink": "/blog/sci-hap-berkeley/page8/",
    "recovered_from": "_site/blog/sci-hap-berkeley/page8/index.html",
    "recovered_at": "2026-04-28",
    "recovered_static_html": true,
    "image": "https://dial-pos-psych.ru/images/sci-hap-berkeley/cover.webp",
    "source_kind": "page"
  },
  {
    "source": "blog/sci-hap-berkeley/page9/index.html",
    "layout": "null",
    "title": "Текстовые материалы курса “Наука о счастье” (Беркли) Страница 9",
    "description": "Текстовые материалы курса “Наука о счастье” (Беркли)",
    "permalink": "/blog/sci-hap-berkeley/page9/",
    "recovered_from": "_site/blog/sci-hap-berkeley/page9/index.html",
    "recovered_at": "2026-04-28",
    "recovered_static_html": true,
    "image": "https://dial-pos-psych.ru/images/sci-hap-berkeley/cover.webp",
    "source_kind": "page"
  },
  {
    "source": "blog/sci-hap-berkeley-vid/index.html",
    "layout": "null",
    "title": "Видеолекции курса Наука о счастье (Беркли)",
    "description": "Все видеолекции из 8-ми недельного курса",
    "permalink": "/blog/sci-hap-berkeley-vid/",
    "recovered_from": "_site/blog/sci-hap-berkeley-vid/index.html",
    "recovered_at": "2026-04-28",
    "recovered_static_html": true,
    "image": "https://dial-pos-psych.ru/images/sci-hap-berkeley-vid/cover.webp",
    "source_kind": "page"
  },
  {
    "source": "blog/term-hap/index.html",
    "layout": "null",
    "title": "Термины счастья",
    "description": "Раздел охватывающий некоторые термины, используемые учеными для определения счастья",
    "permalink": "/blog/term-hap/",
    "recovered_from": "_site/blog/term-hap/index.html",
    "recovered_at": "2026-04-28",
    "recovered_static_html": true,
    "image": "https://dial-pos-psych.ru/images/term-hap/cover.webp",
    "source_kind": "page"
  },
  {
    "source": "blog/weekly-changes-yale/index.html",
    "layout": "null",
    "title": "Ваши еженедельные изменения",
    "description": "Семь практик способствующих благополучию: смакование, благодарность, доброта, социальные связи, физические упражнения, сон и медитация.",
    "permalink": "/blog/weekly-changes-yale/",
    "recovered_from": "_site/blog/weekly-changes-yale/index.html",
    "recovered_at": "2026-04-28",
    "recovered_static_html": true,
    "image": "https://dial-pos-psych.ru/images/weekly-changes-yale/cover.webp",
    "source_kind": "page"
  },
  {
    "source": "free-courses-mine/dev-ch-ab/raz-spos-1/raz-spos-1.html",
    "layout": "null",
    "title": "Создано Camtasia 2022",
    "description": null,
    "permalink": "/free-courses-mine/dev-ch-ab/raz-spos-1/raz-spos-1.html",
    "recovered_from": "_site/free-courses-mine/dev-ch-ab/raz-spos-1/raz-spos-1.html",
    "recovered_at": "2026-04-28",
    "recovered_static_html": true,
    "source_kind": "page"
  },
  {
    "source": "free-courses-mine/dev-ch-ab/raz-spos-1/raz-spos-1_player.html",
    "layout": "null",
    "title": "",
    "description": null,
    "permalink": "/free-courses-mine/dev-ch-ab/raz-spos-1/raz-spos-1_player.html",
    "recovered_from": "_site/free-courses-mine/dev-ch-ab/raz-spos-1/raz-spos-1_player.html",
    "recovered_at": "2026-04-28",
    "recovered_static_html": true,
    "source_kind": "page"
  },
  {
    "source": "free-courses-mine/dev-ch-ab/raz-spos-2/raz-spos-2.html",
    "layout": "null",
    "title": "Создано Camtasia 2022",
    "description": null,
    "permalink": "/free-courses-mine/dev-ch-ab/raz-spos-2/raz-spos-2.html",
    "recovered_from": "_site/free-courses-mine/dev-ch-ab/raz-spos-2/raz-spos-2.html",
    "recovered_at": "2026-04-28",
    "recovered_static_html": true,
    "source_kind": "page"
  },
  {
    "source": "free-courses-mine/dev-ch-ab/raz-spos-2/raz-spos-2_player.html",
    "layout": "null",
    "title": "",
    "description": null,
    "permalink": "/free-courses-mine/dev-ch-ab/raz-spos-2/raz-spos-2_player.html",
    "recovered_from": "_site/free-courses-mine/dev-ch-ab/raz-spos-2/raz-spos-2_player.html",
    "recovered_at": "2026-04-28",
    "recovered_static_html": true,
    "source_kind": "page"
  },
  {
    "source": "free-courses-mine/dev-ch-ab/raz-spos-3/raz-spos-3.html",
    "layout": "null",
    "title": "Создано Camtasia 2022",
    "description": null,
    "permalink": "/free-courses-mine/dev-ch-ab/raz-spos-3/raz-spos-3.html",
    "recovered_from": "_site/free-courses-mine/dev-ch-ab/raz-spos-3/raz-spos-3.html",
    "recovered_at": "2026-04-28",
    "recovered_static_html": true,
    "source_kind": "page"
  },
  {
    "source": "free-courses-mine/dev-ch-ab/raz-spos-3/raz-spos-3_player.html",
    "layout": "null",
    "title": "",
    "description": null,
    "permalink": "/free-courses-mine/dev-ch-ab/raz-spos-3/raz-spos-3_player.html",
    "recovered_from": "_site/free-courses-mine/dev-ch-ab/raz-spos-3/raz-spos-3_player.html",
    "recovered_at": "2026-04-28",
    "recovered_static_html": true,
    "source_kind": "page"
  },
  {
    "source": "free-courses-mine/pos-em-kids/01_intro/01_intro.html",
    "layout": "null",
    "title": "Создано Camtasia 2022",
    "description": null,
    "permalink": "/free-courses-mine/pos-em-kids/01_intro/01_intro.html",
    "recovered_from": "_site/free-courses-mine/pos-em-kids/01_intro/01_intro.html",
    "recovered_at": "2026-04-28",
    "recovered_static_html": true,
    "source_kind": "page"
  },
  {
    "source": "free-courses-mine/pos-em-kids/01_intro/01_intro_player.html",
    "layout": "null",
    "title": "",
    "description": null,
    "permalink": "/free-courses-mine/pos-em-kids/01_intro/01_intro_player.html",
    "recovered_from": "_site/free-courses-mine/pos-em-kids/01_intro/01_intro_player.html",
    "recovered_at": "2026-04-28",
    "recovered_static_html": true,
    "source_kind": "page"
  },
  {
    "source": "free-courses-mine/pos-em-kids/02_joint-sl/02_joint-sl.html",
    "layout": "null",
    "title": "Создано Camtasia 2022",
    "description": null,
    "permalink": "/free-courses-mine/pos-em-kids/02_joint-sl/02_joint-sl.html",
    "recovered_from": "_site/free-courses-mine/pos-em-kids/02_joint-sl/02_joint-sl.html",
    "recovered_at": "2026-04-28",
    "recovered_static_html": true,
    "source_kind": "page"
  },
  {
    "source": "free-courses-mine/pos-em-kids/02_joint-sl/02_joint-sl_player.html",
    "layout": "null",
    "title": "",
    "description": null,
    "permalink": "/free-courses-mine/pos-em-kids/02_joint-sl/02_joint-sl_player.html",
    "recovered_from": "_site/free-courses-mine/pos-em-kids/02_joint-sl/02_joint-sl_player.html",
    "recovered_at": "2026-04-28",
    "recovered_static_html": true,
    "source_kind": "page"
  },
  {
    "source": "free-courses-mine/pos-em-kids/03_sync-games/03_sync-games.html",
    "layout": "null",
    "title": "Создано Camtasia 2022",
    "description": null,
    "permalink": "/free-courses-mine/pos-em-kids/03_sync-games/03_sync-games.html",
    "recovered_from": "_site/free-courses-mine/pos-em-kids/03_sync-games/03_sync-games.html",
    "recovered_at": "2026-04-28",
    "recovered_static_html": true,
    "source_kind": "page"
  },
  {
    "source": "free-courses-mine/pos-em-kids/03_sync-games/03_sync-games_player.html",
    "layout": "null",
    "title": "",
    "description": null,
    "permalink": "/free-courses-mine/pos-em-kids/03_sync-games/03_sync-games_player.html",
    "recovered_from": "_site/free-courses-mine/pos-em-kids/03_sync-games/03_sync-games_player.html",
    "recovered_at": "2026-04-28",
    "recovered_static_html": true,
    "source_kind": "page"
  },
  {
    "source": "free-courses-mine/pos-em-kids/04_yes-no/04_yes-no.html",
    "layout": "null",
    "title": "Создано Camtasia 2022",
    "description": null,
    "permalink": "/free-courses-mine/pos-em-kids/04_yes-no/04_yes-no.html",
    "recovered_from": "_site/free-courses-mine/pos-em-kids/04_yes-no/04_yes-no.html",
    "recovered_at": "2026-04-28",
    "recovered_static_html": true,
    "source_kind": "page"
  },
  {
    "source": "free-courses-mine/pos-em-kids/04_yes-no/04_yes-no_player.html",
    "layout": "null",
    "title": "",
    "description": null,
    "permalink": "/free-courses-mine/pos-em-kids/04_yes-no/04_yes-no_player.html",
    "recovered_from": "_site/free-courses-mine/pos-em-kids/04_yes-no/04_yes-no_player.html",
    "recovered_at": "2026-04-28",
    "recovered_static_html": true,
    "source_kind": "page"
  },
  {
    "source": "free-courses-mine/pos-em-kids/05_sel-pun-pr/05_sel-pun-pr.html",
    "layout": "null",
    "title": "Создано Camtasia 2022",
    "description": null,
    "permalink": "/free-courses-mine/pos-em-kids/05_sel-pun-pr/05_sel-pun-pr.html",
    "recovered_from": "_site/free-courses-mine/pos-em-kids/05_sel-pun-pr/05_sel-pun-pr.html",
    "recovered_at": "2026-04-28",
    "recovered_static_html": true,
    "source_kind": "page"
  },
  {
    "source": "free-courses-mine/pos-em-kids/05_sel-pun-pr/05_sel-pun-pr_player.html",
    "layout": "null",
    "title": "",
    "description": null,
    "permalink": "/free-courses-mine/pos-em-kids/05_sel-pun-pr/05_sel-pun-pr_player.html",
    "recovered_from": "_site/free-courses-mine/pos-em-kids/05_sel-pun-pr/05_sel-pun-pr_player.html",
    "recovered_at": "2026-04-28",
    "recovered_static_html": true,
    "source_kind": "page"
  },
  {
    "source": "free-courses-mine/pos-em-kids/06_prec-min/06_prec-min.html",
    "layout": "null",
    "title": "Создано Camtasia 2022",
    "description": null,
    "permalink": "/free-courses-mine/pos-em-kids/06_prec-min/06_prec-min.html",
    "recovered_from": "_site/free-courses-mine/pos-em-kids/06_prec-min/06_prec-min.html",
    "recovered_at": "2026-04-28",
    "recovered_static_html": true,
    "source_kind": "page"
  },
  {
    "source": "free-courses-mine/pos-em-kids/06_prec-min/06_prec-min_player.html",
    "layout": "null",
    "title": "",
    "description": null,
    "permalink": "/free-courses-mine/pos-em-kids/06_prec-min/06_prec-min_player.html",
    "recovered_from": "_site/free-courses-mine/pos-em-kids/06_prec-min/06_prec-min_player.html",
    "recovered_at": "2026-04-28",
    "recovered_static_html": true,
    "source_kind": "page"
  },
  {
    "source": "free-courses-mine/pos-em-kids/07_contr/07_contr.html",
    "layout": "null",
    "title": "Создано Camtasia 2022",
    "description": null,
    "permalink": "/free-courses-mine/pos-em-kids/07_contr/07_contr.html",
    "recovered_from": "_site/free-courses-mine/pos-em-kids/07_contr/07_contr.html",
    "recovered_at": "2026-04-28",
    "recovered_static_html": true,
    "source_kind": "page"
  },
  {
    "source": "free-courses-mine/pos-em-kids/07_contr/07_contr_player.html",
    "layout": "null",
    "title": "",
    "description": null,
    "permalink": "/free-courses-mine/pos-em-kids/07_contr/07_contr_player.html",
    "recovered_from": "_site/free-courses-mine/pos-em-kids/07_contr/07_contr_player.html",
    "recovered_at": "2026-04-28",
    "recovered_static_html": true,
    "source_kind": "page"
  },
  {
    "source": "free-courses-mine/pos-em-kids/08_ny-pr/08_ny-pr.html",
    "layout": "null",
    "title": "Создано Camtasia 2022",
    "description": null,
    "permalink": "/free-courses-mine/pos-em-kids/08_ny-pr/08_ny-pr.html",
    "recovered_from": "_site/free-courses-mine/pos-em-kids/08_ny-pr/08_ny-pr.html",
    "recovered_at": "2026-04-28",
    "recovered_static_html": true,
    "source_kind": "page"
  },
  {
    "source": "free-courses-mine/pos-em-kids/08_ny-pr/08_ny-pr_player.html",
    "layout": "null",
    "title": "",
    "description": null,
    "permalink": "/free-courses-mine/pos-em-kids/08_ny-pr/08_ny-pr_player.html",
    "recovered_from": "_site/free-courses-mine/pos-em-kids/08_ny-pr/08_ny-pr_player.html",
    "recovered_at": "2026-04-28",
    "recovered_static_html": true,
    "source_kind": "page"
  },
  {
    "source": "free-courses-mine/pos-em-kids/09_concl/09_concl.html",
    "layout": "null",
    "title": "Создано Camtasia 2022",
    "description": null,
    "permalink": "/free-courses-mine/pos-em-kids/09_concl/09_concl.html",
    "recovered_from": "_site/free-courses-mine/pos-em-kids/09_concl/09_concl.html",
    "recovered_at": "2026-04-28",
    "recovered_static_html": true,
    "source_kind": "page"
  },
  {
    "source": "free-courses-mine/pos-em-kids/09_concl/09_concl_player.html",
    "layout": "null",
    "title": "",
    "description": null,
    "permalink": "/free-courses-mine/pos-em-kids/09_concl/09_concl_player.html",
    "recovered_from": "_site/free-courses-mine/pos-em-kids/09_concl/09_concl_player.html",
    "recovered_at": "2026-04-28",
    "recovered_static_html": true,
    "source_kind": "page"
  },
  {
    "source": "google61746351e85d8086.html",
    "layout": "null",
    "title": null,
    "description": null,
    "permalink": "/google61746351e85d8086.html",
    "recovered_from": "_site/google61746351e85d8086.html",
    "recovered_at": "2026-04-28",
    "recovered_static_html": true,
    "source_kind": "page"
  },
  {
    "source": "index.html",
    "layout": "null",
    "title": "Диалектическая позитивная психология",
    "description": "Об искусстве жить, опираясь на материалистическую диалектику и позитивную психологию",
    "permalink": "/",
    "recovered_from": "_site/index.html",
    "recovered_at": "2026-04-28",
    "recovered_static_html": true,
    "body_class": "home-page",
    "source_kind": "page"
  },
  {
    "source": "ker/00-intr/m/00-intr.html",
    "layout": "null",
    "title": "",
    "description": null,
    "permalink": "/ker/00-intr/m/00-intr.html",
    "recovered_from": "_site/ker/00-intr/m/00-intr.html",
    "recovered_at": "2026-04-28",
    "recovered_static_html": true,
    "body_class": "standalone-viewer",
    "source_kind": "page"
  },
  {
    "source": "ker/00-intr/v/00-intr.html",
    "layout": "null",
    "title": "Введение",
    "description": null,
    "permalink": "/ker/00-intr/v/00-intr.html",
    "recovered_from": "_site/ker/00-intr/v/00-intr.html",
    "recovered_at": "2026-04-28",
    "recovered_static_html": true,
    "source_kind": "page"
  },
  {
    "source": "ker/00-intr/v/00-intr_player.html",
    "layout": "null",
    "title": "",
    "description": null,
    "permalink": "/ker/00-intr/v/00-intr_player.html",
    "recovered_from": "_site/ker/00-intr/v/00-intr_player.html",
    "recovered_at": "2026-04-28",
    "recovered_static_html": true,
    "source_kind": "page"
  },
  {
    "source": "ker/01-nat-par/m/01-nat-par.html",
    "layout": "null",
    "title": "",
    "description": null,
    "permalink": "/ker/01-nat-par/m/01-nat-par.html",
    "recovered_from": "_site/ker/01-nat-par/m/01-nat-par.html",
    "recovered_at": "2026-04-28",
    "recovered_static_html": true,
    "body_class": "standalone-viewer",
    "source_kind": "page"
  },
  {
    "source": "ker/01-nat-par/v/01-nat-par.html",
    "layout": "null",
    "title": "Тема № 01. Естественные родители",
    "description": null,
    "permalink": "/ker/01-nat-par/v/01-nat-par.html",
    "recovered_from": "_site/ker/01-nat-par/v/01-nat-par.html",
    "recovered_at": "2026-04-28",
    "recovered_static_html": true,
    "source_kind": "page"
  },
  {
    "source": "ker/01-nat-par/v/01-nat-par_player.html",
    "layout": "null",
    "title": "",
    "description": null,
    "permalink": "/ker/01-nat-par/v/01-nat-par_player.html",
    "recovered_from": "_site/ker/01-nat-par/v/01-nat-par_player.html",
    "recovered_at": "2026-04-28",
    "recovered_static_html": true,
    "source_kind": "page"
  },
  {
    "source": "ker/02-tech-attr/m/02-tech-attr-mat.html",
    "layout": "null",
    "title": "",
    "description": null,
    "permalink": "/ker/02-tech-attr/m/02-tech-attr-mat.html",
    "recovered_from": "_site/ker/02-tech-attr/m/02-tech-attr-mat.html",
    "recovered_at": "2026-04-28",
    "recovered_static_html": true,
    "body_class": "standalone-viewer",
    "source_kind": "page"
  },
  {
    "source": "ker/02-tech-attr/m/02-tech-attr.html",
    "layout": "null",
    "title": "",
    "description": null,
    "permalink": "/ker/02-tech-attr/m/02-tech-attr.html",
    "recovered_from": "_site/ker/02-tech-attr/m/02-tech-attr.html",
    "recovered_at": "2026-04-28",
    "recovered_static_html": true,
    "body_class": "standalone-viewer",
    "source_kind": "page"
  },
  {
    "source": "ker/02-tech-attr/v/02-tech-attr.html",
    "layout": "null",
    "title": "Тема № 02. Техника определения  принадлежности проблемы",
    "description": null,
    "permalink": "/ker/02-tech-attr/v/02-tech-attr.html",
    "recovered_from": "_site/ker/02-tech-attr/v/02-tech-attr.html",
    "recovered_at": "2026-04-28",
    "recovered_static_html": true,
    "source_kind": "page"
  },
  {
    "source": "ker/02-tech-attr/v/02-tech-attr_player.html",
    "layout": "null",
    "title": "",
    "description": null,
    "permalink": "/ker/02-tech-attr/v/02-tech-attr_player.html",
    "recovered_from": "_site/ker/02-tech-attr/v/02-tech-attr_player.html",
    "recovered_at": "2026-04-28",
    "recovered_static_html": true,
    "source_kind": "page"
  },
  {
    "source": "ker/03-typ-12/m/03-typ-12.html",
    "layout": "null",
    "title": "",
    "description": null,
    "permalink": "/ker/03-typ-12/m/03-typ-12.html",
    "recovered_from": "_site/ker/03-typ-12/m/03-typ-12.html",
    "recovered_at": "2026-04-28",
    "recovered_static_html": true,
    "body_class": "standalone-viewer",
    "source_kind": "page"
  },
  {
    "source": "ker/03-typ-12/v/03-typ-12.html",
    "layout": "null",
    "title": "Тема № 03.  \"Типичные 12\"",
    "description": null,
    "permalink": "/ker/03-typ-12/v/03-typ-12.html",
    "recovered_from": "_site/ker/03-typ-12/v/03-typ-12.html",
    "recovered_at": "2026-04-28",
    "recovered_static_html": true,
    "source_kind": "page"
  },
  {
    "source": "ker/03-typ-12/v/03-typ-12_player.html",
    "layout": "null",
    "title": "",
    "description": null,
    "permalink": "/ker/03-typ-12/v/03-typ-12_player.html",
    "recovered_from": "_site/ker/03-typ-12/v/03-typ-12_player.html",
    "recovered_at": "2026-04-28",
    "recovered_static_html": true,
    "source_kind": "page"
  },
  {
    "source": "ker/04-lang-appr1/m/04-lang-appr.html",
    "layout": "null",
    "title": "",
    "description": null,
    "permalink": "/ker/04-lang-appr1/m/04-lang-appr.html",
    "recovered_from": "_site/ker/04-lang-appr1/m/04-lang-appr.html",
    "recovered_at": "2026-04-28",
    "recovered_static_html": true,
    "body_class": "standalone-viewer",
    "source_kind": "page"
  },
  {
    "source": "ker/04-lang-appr1/v/04-lang-appr1.html",
    "layout": "null",
    "title": "Тема № 04. Язык одобрения. Часть 1",
    "description": null,
    "permalink": "/ker/04-lang-appr1/v/04-lang-appr1.html",
    "recovered_from": "_site/ker/04-lang-appr1/v/04-lang-appr1.html",
    "recovered_at": "2026-04-28",
    "recovered_static_html": true,
    "source_kind": "page"
  },
  {
    "source": "ker/04-lang-appr1/v/04-lang-appr1_player.html",
    "layout": "null",
    "title": "",
    "description": null,
    "permalink": "/ker/04-lang-appr1/v/04-lang-appr1_player.html",
    "recovered_from": "_site/ker/04-lang-appr1/v/04-lang-appr1_player.html",
    "recovered_at": "2026-04-28",
    "recovered_static_html": true,
    "source_kind": "page"
  },
  {
    "source": "ker/04-lang-appr2/v/04-lang-appr2.html",
    "layout": "null",
    "title": "Тема № 04. Язык одобрения. Часть 2",
    "description": null,
    "permalink": "/ker/04-lang-appr2/v/04-lang-appr2.html",
    "recovered_from": "_site/ker/04-lang-appr2/v/04-lang-appr2.html",
    "recovered_at": "2026-04-28",
    "recovered_static_html": true,
    "source_kind": "page"
  },
  {
    "source": "ker/04-lang-appr2/v/04-lang-appr2_player.html",
    "layout": "null",
    "title": "",
    "description": null,
    "permalink": "/ker/04-lang-appr2/v/04-lang-appr2_player.html",
    "recovered_from": "_site/ker/04-lang-appr2/v/04-lang-appr2_player.html",
    "recovered_at": "2026-04-28",
    "recovered_static_html": true,
    "source_kind": "page"
  },
  {
    "source": "ker/05-inef-ways/m/05-inef-ways.html",
    "layout": "null",
    "title": "",
    "description": null,
    "permalink": "/ker/05-inef-ways/m/05-inef-ways.html",
    "recovered_from": "_site/ker/05-inef-ways/m/05-inef-ways.html",
    "recovered_at": "2026-04-28",
    "recovered_static_html": true,
    "body_class": "standalone-viewer",
    "source_kind": "page"
  },
  {
    "source": "ker/05-inef-ways/v/05-inef-ways.html",
    "layout": "null",
    "title": "Тема № 05. Неэффективные способы противостояния детям",
    "description": null,
    "permalink": "/ker/05-inef-ways/v/05-inef-ways.html",
    "recovered_from": "_site/ker/05-inef-ways/v/05-inef-ways.html",
    "recovered_at": "2026-04-28",
    "recovered_static_html": true,
    "source_kind": "page"
  },
  {
    "source": "ker/05-inef-ways/v/05-inef-ways_player.html",
    "layout": "null",
    "title": "",
    "description": null,
    "permalink": "/ker/05-inef-ways/v/05-inef-ways_player.html",
    "recovered_from": "_site/ker/05-inef-ways/v/05-inef-ways_player.html",
    "recovered_at": "2026-04-28",
    "recovered_static_html": true,
    "source_kind": "page"
  },
  {
    "source": "ker/06-i-rep/m/06-i-rep.html",
    "layout": "null",
    "title": "",
    "description": null,
    "permalink": "/ker/06-i-rep/m/06-i-rep.html",
    "recovered_from": "_site/ker/06-i-rep/m/06-i-rep.html",
    "recovered_at": "2026-04-28",
    "recovered_static_html": true,
    "body_class": "standalone-viewer",
    "source_kind": "page"
  },
  {
    "source": "ker/06-i-rep/v/06-i-rep.html",
    "layout": "null",
    "title": "Тема № 06. Я-сообщения",
    "description": null,
    "permalink": "/ker/06-i-rep/v/06-i-rep.html",
    "recovered_from": "_site/ker/06-i-rep/v/06-i-rep.html",
    "recovered_at": "2026-04-28",
    "recovered_static_html": true,
    "source_kind": "page"
  },
  {
    "source": "ker/06-i-rep/v/06-i-rep_player.html",
    "layout": "null",
    "title": "",
    "description": null,
    "permalink": "/ker/06-i-rep/v/06-i-rep_player.html",
    "recovered_from": "_site/ker/06-i-rep/v/06-i-rep_player.html",
    "recovered_at": "2026-04-28",
    "recovered_static_html": true,
    "source_kind": "page"
  },
  {
    "source": "ker/07-mod-beh/m/07-mod-beh.html",
    "layout": "null",
    "title": "",
    "description": null,
    "permalink": "/ker/07-mod-beh/m/07-mod-beh.html",
    "recovered_from": "_site/ker/07-mod-beh/m/07-mod-beh.html",
    "recovered_at": "2026-04-28",
    "recovered_static_html": true,
    "body_class": "standalone-viewer",
    "source_kind": "page"
  },
  {
    "source": "ker/07-mod-beh/v/07-mod-beh.html",
    "layout": "null",
    "title": "Тема № 07. Изменение неприемлемого поведения ребенка путем изменения окружающей обстановки",
    "description": null,
    "permalink": "/ker/07-mod-beh/v/07-mod-beh.html",
    "recovered_from": "_site/ker/07-mod-beh/v/07-mod-beh.html",
    "recovered_at": "2026-04-28",
    "recovered_static_html": true,
    "source_kind": "page"
  },
  {
    "source": "ker/07-mod-beh/v/07-mod-beh_player.html",
    "layout": "null",
    "title": "",
    "description": null,
    "permalink": "/ker/07-mod-beh/v/07-mod-beh_player.html",
    "recovered_from": "_site/ker/07-mod-beh/v/07-mod-beh_player.html",
    "recovered_at": "2026-04-28",
    "recovered_static_html": true,
    "source_kind": "page"
  },
  {
    "source": "ker/08-par-pow/m/08-par-pow.html",
    "layout": "null",
    "title": "",
    "description": null,
    "permalink": "/ker/08-par-pow/m/08-par-pow.html",
    "recovered_from": "_site/ker/08-par-pow/m/08-par-pow.html",
    "recovered_at": "2026-04-28",
    "recovered_static_html": true,
    "body_class": "standalone-viewer",
    "source_kind": "page"
  },
  {
    "source": "ker/08-par-pow/v/08-par-pow.html",
    "layout": "null",
    "title": "Тема № 08. Родительская власть",
    "description": null,
    "permalink": "/ker/08-par-pow/v/08-par-pow.html",
    "recovered_from": "_site/ker/08-par-pow/v/08-par-pow.html",
    "recovered_at": "2026-04-28",
    "recovered_static_html": true,
    "source_kind": "page"
  },
  {
    "source": "ker/08-par-pow/v/08-par-pow_player.html",
    "layout": "null",
    "title": "",
    "description": null,
    "permalink": "/ker/08-par-pow/v/08-par-pow_player.html",
    "recovered_from": "_site/ker/08-par-pow/v/08-par-pow_player.html",
    "recovered_at": "2026-04-28",
    "recovered_static_html": true,
    "source_kind": "page"
  },
  {
    "source": "ker/09-conflict/m/09-conflict.html",
    "layout": "null",
    "title": "",
    "description": null,
    "permalink": "/ker/09-conflict/m/09-conflict.html",
    "recovered_from": "_site/ker/09-conflict/m/09-conflict.html",
    "recovered_at": "2026-04-28",
    "recovered_static_html": true,
    "body_class": "standalone-viewer",
    "source_kind": "page"
  },
  {
    "source": "ker/09-conflict/v/09-conflict.html",
    "layout": "null",
    "title": "Тема № 09. Кофликт",
    "description": null,
    "permalink": "/ker/09-conflict/v/09-conflict.html",
    "recovered_from": "_site/ker/09-conflict/v/09-conflict.html",
    "recovered_at": "2026-04-28",
    "recovered_static_html": true,
    "source_kind": "page"
  },
  {
    "source": "ker/09-conflict/v/09-conflict_player.html",
    "layout": "null",
    "title": "",
    "description": null,
    "permalink": "/ker/09-conflict/v/09-conflict_player.html",
    "recovered_from": "_site/ker/09-conflict/v/09-conflict_player.html",
    "recovered_at": "2026-04-28",
    "recovered_static_html": true,
    "source_kind": "page"
  },
  {
    "source": "ker/10-values/m/10-values.html",
    "layout": "null",
    "title": "",
    "description": null,
    "permalink": "/ker/10-values/m/10-values.html",
    "recovered_from": "_site/ker/10-values/m/10-values.html",
    "recovered_at": "2026-04-28",
    "recovered_static_html": true,
    "body_class": "standalone-viewer",
    "source_kind": "page"
  },
  {
    "source": "ker/10-values/v/10-values.html",
    "layout": "null",
    "title": "Тема № 10. О ценностях",
    "description": null,
    "permalink": "/ker/10-values/v/10-values.html",
    "recovered_from": "_site/ker/10-values/v/10-values.html",
    "recovered_at": "2026-04-28",
    "recovered_static_html": true,
    "source_kind": "page"
  },
  {
    "source": "ker/10-values/v/10-values_player.html",
    "layout": "null",
    "title": "",
    "description": null,
    "permalink": "/ker/10-values/v/10-values_player.html",
    "recovered_from": "_site/ker/10-values/v/10-values_player.html",
    "recovered_at": "2026-04-28",
    "recovered_static_html": true,
    "source_kind": "page"
  },
  {
    "source": "ker/11-final/m/11-final.html",
    "layout": "null",
    "title": "",
    "description": null,
    "permalink": "/ker/11-final/m/11-final.html",
    "recovered_from": "_site/ker/11-final/m/11-final.html",
    "recovered_at": "2026-04-28",
    "recovered_static_html": true,
    "body_class": "standalone-viewer",
    "source_kind": "page"
  },
  {
    "source": "ker/11-final/v/11-final.html",
    "layout": "null",
    "title": "Заключительное занятие",
    "description": null,
    "permalink": "/ker/11-final/v/11-final.html",
    "recovered_from": "_site/ker/11-final/v/11-final.html",
    "recovered_at": "2026-04-28",
    "recovered_static_html": true,
    "source_kind": "page"
  },
  {
    "source": "ker/11-final/v/11-final_player.html",
    "layout": "null",
    "title": "",
    "description": null,
    "permalink": "/ker/11-final/v/11-final_player.html",
    "recovered_from": "_site/ker/11-final/v/11-final_player.html",
    "recovered_at": "2026-04-28",
    "recovered_static_html": true,
    "source_kind": "page"
  },
  {
    "source": "ker/ker.html",
    "layout": "null",
    "title": "",
    "description": null,
    "permalink": "/ker/ker.html",
    "recovered_from": "_site/ker/ker.html",
    "recovered_at": "2026-04-28",
    "recovered_static_html": true,
    "body_class": "standalone-viewer",
    "source_kind": "page"
  },
  {
    "source": "ker/kerforyulia.html",
    "layout": "null",
    "title": "",
    "description": null,
    "permalink": "/ker/kerforyulia.html",
    "recovered_from": "_site/ker/kerforyulia.html",
    "recovered_at": "2026-04-28",
    "recovered_static_html": true,
    "body_class": "standalone-viewer",
    "source_kind": "page"
  },
  {
    "source": "ker-wp/01-nat-par.html",
    "layout": "null",
    "title": "",
    "description": null,
    "permalink": "/ker-wp/01-nat-par.html",
    "recovered_from": "_site/ker-wp/01-nat-par.html",
    "recovered_at": "2026-04-28",
    "recovered_static_html": true,
    "body_class": "standalone-viewer",
    "source_kind": "page"
  },
  {
    "source": "ker-wp/02-tech-attr.html",
    "layout": "null",
    "title": "",
    "description": null,
    "permalink": "/ker-wp/02-tech-attr.html",
    "recovered_from": "_site/ker-wp/02-tech-attr.html",
    "recovered_at": "2026-04-28",
    "recovered_static_html": true,
    "body_class": "standalone-viewer",
    "source_kind": "page"
  },
  {
    "source": "ker-wp/03-typ-12.html",
    "layout": "null",
    "title": "",
    "description": null,
    "permalink": "/ker-wp/03-typ-12.html",
    "recovered_from": "_site/ker-wp/03-typ-12.html",
    "recovered_at": "2026-04-28",
    "recovered_static_html": true,
    "body_class": "standalone-viewer",
    "source_kind": "page"
  },
  {
    "source": "ker-wp/04-lang-appr.html",
    "layout": "null",
    "title": "",
    "description": null,
    "permalink": "/ker-wp/04-lang-appr.html",
    "recovered_from": "_site/ker-wp/04-lang-appr.html",
    "recovered_at": "2026-04-28",
    "recovered_static_html": true,
    "body_class": "standalone-viewer",
    "source_kind": "page"
  },
  {
    "source": "ker-wp/05-inef-ways.html",
    "layout": "null",
    "title": "",
    "description": null,
    "permalink": "/ker-wp/05-inef-ways.html",
    "recovered_from": "_site/ker-wp/05-inef-ways.html",
    "recovered_at": "2026-04-28",
    "recovered_static_html": true,
    "body_class": "standalone-viewer",
    "source_kind": "page"
  },
  {
    "source": "ker-wp/06-i-rep.html",
    "layout": "null",
    "title": "",
    "description": null,
    "permalink": "/ker-wp/06-i-rep.html",
    "recovered_from": "_site/ker-wp/06-i-rep.html",
    "recovered_at": "2026-04-28",
    "recovered_static_html": true,
    "body_class": "standalone-viewer",
    "source_kind": "page"
  },
  {
    "source": "ker-wp/07-mod-beh.html",
    "layout": "null",
    "title": "",
    "description": null,
    "permalink": "/ker-wp/07-mod-beh.html",
    "recovered_from": "_site/ker-wp/07-mod-beh.html",
    "recovered_at": "2026-04-28",
    "recovered_static_html": true,
    "body_class": "standalone-viewer",
    "source_kind": "page"
  },
  {
    "source": "ker-wp/08-par-pow.html",
    "layout": "null",
    "title": "",
    "description": null,
    "permalink": "/ker-wp/08-par-pow.html",
    "recovered_from": "_site/ker-wp/08-par-pow.html",
    "recovered_at": "2026-04-28",
    "recovered_static_html": true,
    "body_class": "standalone-viewer",
    "source_kind": "page"
  },
  {
    "source": "ker-wp/09-conflict.html",
    "layout": "null",
    "title": "",
    "description": null,
    "permalink": "/ker-wp/09-conflict.html",
    "recovered_from": "_site/ker-wp/09-conflict.html",
    "recovered_at": "2026-04-28",
    "recovered_static_html": true,
    "body_class": "standalone-viewer",
    "source_kind": "page"
  },
  {
    "source": "ker-wp/10-values.html",
    "layout": "null",
    "title": "",
    "description": null,
    "permalink": "/ker-wp/10-values.html",
    "recovered_from": "_site/ker-wp/10-values.html",
    "recovered_at": "2026-04-28",
    "recovered_static_html": true,
    "body_class": "standalone-viewer",
    "source_kind": "page"
  },
  {
    "source": "ker-wp/11-final.html",
    "layout": "null",
    "title": "",
    "description": null,
    "permalink": "/ker-wp/11-final.html",
    "recovered_from": "_site/ker-wp/11-final.html",
    "recovered_at": "2026-04-28",
    "recovered_static_html": true,
    "body_class": "standalone-viewer",
    "source_kind": "page"
  },
  {
    "source": "ker-wp/DemoVideosKer/01/01.html",
    "layout": "null",
    "title": "Создано Camtasia 2022",
    "description": null,
    "permalink": "/ker-wp/DemoVideosKer/01/01.html",
    "recovered_from": "_site/ker-wp/DemoVideosKer/01/01.html",
    "recovered_at": "2026-04-28",
    "recovered_static_html": true,
    "source_kind": "page"
  },
  {
    "source": "ker-wp/DemoVideosKer/01/01_player.html",
    "layout": "null",
    "title": "",
    "description": null,
    "permalink": "/ker-wp/DemoVideosKer/01/01_player.html",
    "recovered_from": "_site/ker-wp/DemoVideosKer/01/01_player.html",
    "recovered_at": "2026-04-28",
    "recovered_static_html": true,
    "source_kind": "page"
  },
  {
    "source": "ker-wp/DemoVideosKer/02/02.html",
    "layout": "null",
    "title": "Создано Camtasia 2022",
    "description": null,
    "permalink": "/ker-wp/DemoVideosKer/02/02.html",
    "recovered_from": "_site/ker-wp/DemoVideosKer/02/02.html",
    "recovered_at": "2026-04-28",
    "recovered_static_html": true,
    "source_kind": "page"
  },
  {
    "source": "ker-wp/DemoVideosKer/02/02_player.html",
    "layout": "null",
    "title": "",
    "description": null,
    "permalink": "/ker-wp/DemoVideosKer/02/02_player.html",
    "recovered_from": "_site/ker-wp/DemoVideosKer/02/02_player.html",
    "recovered_at": "2026-04-28",
    "recovered_static_html": true,
    "source_kind": "page"
  },
  {
    "source": "ker-wp/DemoVideosKer/03/03.html",
    "layout": "null",
    "title": "Создано Camtasia 2022",
    "description": null,
    "permalink": "/ker-wp/DemoVideosKer/03/03.html",
    "recovered_from": "_site/ker-wp/DemoVideosKer/03/03.html",
    "recovered_at": "2026-04-28",
    "recovered_static_html": true,
    "source_kind": "page"
  },
  {
    "source": "ker-wp/DemoVideosKer/03/03_player.html",
    "layout": "null",
    "title": "",
    "description": null,
    "permalink": "/ker-wp/DemoVideosKer/03/03_player.html",
    "recovered_from": "_site/ker-wp/DemoVideosKer/03/03_player.html",
    "recovered_at": "2026-04-28",
    "recovered_static_html": true,
    "source_kind": "page"
  },
  {
    "source": "ker-wp/DemoVideosKer/04-01/04-01.html",
    "layout": "null",
    "title": "Создано Camtasia 2022",
    "description": null,
    "permalink": "/ker-wp/DemoVideosKer/04-01/04-01.html",
    "recovered_from": "_site/ker-wp/DemoVideosKer/04-01/04-01.html",
    "recovered_at": "2026-04-28",
    "recovered_static_html": true,
    "source_kind": "page"
  },
  {
    "source": "ker-wp/DemoVideosKer/04-01/04-01_player.html",
    "layout": "null",
    "title": "",
    "description": null,
    "permalink": "/ker-wp/DemoVideosKer/04-01/04-01_player.html",
    "recovered_from": "_site/ker-wp/DemoVideosKer/04-01/04-01_player.html",
    "recovered_at": "2026-04-28",
    "recovered_static_html": true,
    "source_kind": "page"
  },
  {
    "source": "ker-wp/DemoVideosKer/04-02/04-02.html",
    "layout": "null",
    "title": "Создано Camtasia 2022",
    "description": null,
    "permalink": "/ker-wp/DemoVideosKer/04-02/04-02.html",
    "recovered_from": "_site/ker-wp/DemoVideosKer/04-02/04-02.html",
    "recovered_at": "2026-04-28",
    "recovered_static_html": true,
    "source_kind": "page"
  },
  {
    "source": "ker-wp/DemoVideosKer/04-02/04-02_player.html",
    "layout": "null",
    "title": "",
    "description": null,
    "permalink": "/ker-wp/DemoVideosKer/04-02/04-02_player.html",
    "recovered_from": "_site/ker-wp/DemoVideosKer/04-02/04-02_player.html",
    "recovered_at": "2026-04-28",
    "recovered_static_html": true,
    "source_kind": "page"
  },
  {
    "source": "ker-wp/DemoVideosKer/05/05.html",
    "layout": "null",
    "title": "Создано Camtasia 2022",
    "description": null,
    "permalink": "/ker-wp/DemoVideosKer/05/05.html",
    "recovered_from": "_site/ker-wp/DemoVideosKer/05/05.html",
    "recovered_at": "2026-04-28",
    "recovered_static_html": true,
    "source_kind": "page"
  },
  {
    "source": "ker-wp/DemoVideosKer/05/05_player.html",
    "layout": "null",
    "title": "",
    "description": null,
    "permalink": "/ker-wp/DemoVideosKer/05/05_player.html",
    "recovered_from": "_site/ker-wp/DemoVideosKer/05/05_player.html",
    "recovered_at": "2026-04-28",
    "recovered_static_html": true,
    "source_kind": "page"
  },
  {
    "source": "ker-wp/DemoVideosKer/06/06.html",
    "layout": "null",
    "title": "Создано Camtasia 2022",
    "description": null,
    "permalink": "/ker-wp/DemoVideosKer/06/06.html",
    "recovered_from": "_site/ker-wp/DemoVideosKer/06/06.html",
    "recovered_at": "2026-04-28",
    "recovered_static_html": true,
    "source_kind": "page"
  },
  {
    "source": "ker-wp/DemoVideosKer/06/06_player.html",
    "layout": "null",
    "title": "",
    "description": null,
    "permalink": "/ker-wp/DemoVideosKer/06/06_player.html",
    "recovered_from": "_site/ker-wp/DemoVideosKer/06/06_player.html",
    "recovered_at": "2026-04-28",
    "recovered_static_html": true,
    "source_kind": "page"
  },
  {
    "source": "ker-wp/DemoVideosKer/07/07.html",
    "layout": "null",
    "title": "Создано Camtasia 2022",
    "description": null,
    "permalink": "/ker-wp/DemoVideosKer/07/07.html",
    "recovered_from": "_site/ker-wp/DemoVideosKer/07/07.html",
    "recovered_at": "2026-04-28",
    "recovered_static_html": true,
    "source_kind": "page"
  },
  {
    "source": "ker-wp/DemoVideosKer/07/07_player.html",
    "layout": "null",
    "title": "",
    "description": null,
    "permalink": "/ker-wp/DemoVideosKer/07/07_player.html",
    "recovered_from": "_site/ker-wp/DemoVideosKer/07/07_player.html",
    "recovered_at": "2026-04-28",
    "recovered_static_html": true,
    "source_kind": "page"
  },
  {
    "source": "ker-wp/DemoVideosKer/08/08.html",
    "layout": "null",
    "title": "Создано Camtasia 2022",
    "description": null,
    "permalink": "/ker-wp/DemoVideosKer/08/08.html",
    "recovered_from": "_site/ker-wp/DemoVideosKer/08/08.html",
    "recovered_at": "2026-04-28",
    "recovered_static_html": true,
    "source_kind": "page"
  },
  {
    "source": "ker-wp/DemoVideosKer/08/08_player.html",
    "layout": "null",
    "title": "",
    "description": null,
    "permalink": "/ker-wp/DemoVideosKer/08/08_player.html",
    "recovered_from": "_site/ker-wp/DemoVideosKer/08/08_player.html",
    "recovered_at": "2026-04-28",
    "recovered_static_html": true,
    "source_kind": "page"
  },
  {
    "source": "ker-wp/DemoVideosKer/09/09.html",
    "layout": "null",
    "title": "Создано Camtasia 2022",
    "description": null,
    "permalink": "/ker-wp/DemoVideosKer/09/09.html",
    "recovered_from": "_site/ker-wp/DemoVideosKer/09/09.html",
    "recovered_at": "2026-04-28",
    "recovered_static_html": true,
    "source_kind": "page"
  },
  {
    "source": "ker-wp/DemoVideosKer/09/09_player.html",
    "layout": "null",
    "title": "",
    "description": null,
    "permalink": "/ker-wp/DemoVideosKer/09/09_player.html",
    "recovered_from": "_site/ker-wp/DemoVideosKer/09/09_player.html",
    "recovered_at": "2026-04-28",
    "recovered_static_html": true,
    "source_kind": "page"
  },
  {
    "source": "ker-wp/DemoVideosKer/10/10.html",
    "layout": "null",
    "title": "Создано Camtasia 2022",
    "description": null,
    "permalink": "/ker-wp/DemoVideosKer/10/10.html",
    "recovered_from": "_site/ker-wp/DemoVideosKer/10/10.html",
    "recovered_at": "2026-04-28",
    "recovered_static_html": true,
    "source_kind": "page"
  },
  {
    "source": "ker-wp/DemoVideosKer/10/10_player.html",
    "layout": "null",
    "title": "",
    "description": null,
    "permalink": "/ker-wp/DemoVideosKer/10/10_player.html",
    "recovered_from": "_site/ker-wp/DemoVideosKer/10/10_player.html",
    "recovered_at": "2026-04-28",
    "recovered_static_html": true,
    "source_kind": "page"
  },
  {
    "source": "ker-wp/videoinstrisp/videoinstrisp.html",
    "layout": "null",
    "title": "Создано Camtasia 2022",
    "description": null,
    "permalink": "/ker-wp/videoinstrisp/videoinstrisp.html",
    "recovered_from": "_site/ker-wp/videoinstrisp/videoinstrisp.html",
    "recovered_at": "2026-04-28",
    "recovered_static_html": true,
    "source_kind": "page"
  },
  {
    "source": "ker-wp/videoinstrisp/videoinstrisp_player.html",
    "layout": "null",
    "title": "",
    "description": null,
    "permalink": "/ker-wp/videoinstrisp/videoinstrisp_player.html",
    "recovered_from": "_site/ker-wp/videoinstrisp/videoinstrisp_player.html",
    "recovered_at": "2026-04-28",
    "recovered_static_html": true,
    "source_kind": "page"
  },
  {
    "source": "ker-wp/videoinstrpok/videoinstrpok.html",
    "layout": "null",
    "title": "Создано Camtasia 2022",
    "description": null,
    "permalink": "/ker-wp/videoinstrpok/videoinstrpok.html",
    "recovered_from": "_site/ker-wp/videoinstrpok/videoinstrpok.html",
    "recovered_at": "2026-04-28",
    "recovered_static_html": true,
    "source_kind": "page"
  },
  {
    "source": "ker-wp/videoinstrpok/videoinstrpok_player.html",
    "layout": "null",
    "title": "",
    "description": null,
    "permalink": "/ker-wp/videoinstrpok/videoinstrpok_player.html",
    "recovered_from": "_site/ker-wp/videoinstrpok/videoinstrpok_player.html",
    "recovered_at": "2026-04-28",
    "recovered_static_html": true,
    "source_kind": "page"
  },
  {
    "source": "map/index.html",
    "layout": "null",
    "title": "Диалектическая позитивная психология",
    "description": "Об искусстве жить, опираясь на материалистическую диалектику и позитивную психологию",
    "permalink": "/map/",
    "recovered_from": "_site/map/index.html",
    "recovered_at": "2026-04-28",
    "recovered_static_html": true,
    "source_kind": "page"
  },
  {
    "source": "map/my-personal-mission.html",
    "layout": "null",
    "title": "",
    "description": null,
    "permalink": "/map/my-personal-mission.html",
    "recovered_from": "_site/map/my-personal-mission.html",
    "recovered_at": "2026-04-28",
    "recovered_static_html": true,
    "body_class": "standalone-viewer",
    "source_kind": "page"
  },
  {
    "source": "otkaz-ot-otvetstvennosti.html",
    "layout": "null",
    "title": "Диалектическая позитивная психология",
    "description": "Об искусстве жить, опираясь на материалистическую диалектику и позитивную психологию",
    "permalink": "/otkaz-ot-otvetstvennosti.html",
    "recovered_from": "_site/otkaz-ot-otvetstvennosti.html",
    "recovered_at": "2026-04-28",
    "recovered_static_html": true,
    "source_kind": "page"
  },
  {
    "source": "politika-konfidentcialnosti.html",
    "layout": "null",
    "title": "Диалектическая позитивная психология",
    "description": "Об искусстве жить, опираясь на материалистическую диалектику и позитивную психологию",
    "permalink": "/politika-konfidentcialnosti.html",
    "recovered_from": "_site/politika-konfidentcialnosti.html",
    "recovered_at": "2026-04-28",
    "recovered_static_html": true,
    "source_kind": "page"
  },
  {
    "source": "post.html",
    "layout": "null",
    "title": null,
    "description": null,
    "permalink": "/post.html",
    "recovered_from": "_site/post.html",
    "recovered_at": "2026-04-28",
    "recovered_static_html": true,
    "source_kind": "page"
  },
  {
    "source": "search.html",
    "layout": "null",
    "title": "Диалектическая позитивная психология",
    "description": "Об искусстве жить, опираясь на материалистическую диалектику и позитивную психологию",
    "permalink": "/search.html",
    "recovered_from": "_site/search.html",
    "recovered_at": "2026-04-28",
    "recovered_static_html": true,
    "source_kind": "page"
  },
  {
    "source": "site-map.html",
    "layout": "null",
    "title": "Диалектическая позитивная психология",
    "description": "Об искусстве жить, опираясь на материалистическую диалектику и позитивную психологию",
    "permalink": "/site-map.html",
    "recovered_from": "_site/site-map.html",
    "recovered_at": "2026-04-28",
    "recovered_static_html": true,
    "source_kind": "page"
  },
  {
    "source": "soglasie-na-rassylku.html",
    "layout": "null",
    "title": "Диалектическая позитивная психология",
    "description": "Об искусстве жить, опираясь на материалистическую диалектику и позитивную психологию",
    "permalink": "/soglasie-na-rassylku.html",
    "recovered_from": "_site/soglasie-na-rassylku.html",
    "recovered_at": "2026-04-28",
    "recovered_static_html": true,
    "source_kind": "page"
  }
]
